agadoodoo/__init__.py
agadoodoo/__main__.py
agadoodoo/__version__.py
agadoodoo/cli/__init__.py
agadoodoo/cli/application.py
agadoodoo/cli/commands/__init__.py
agadoodoo/cli/commands/test.py
agadoodoo-0.1.12.dist-info/entry_points.txt
agadoodoo-0.1.12.dist-info/WHEEL
agadoodoo-0.1.12.dist-info/METADATA
agadoodoo-0.1.12.dist-info/RECORD
