Metadata-Version: 2.1
Name: agadoodoo
Version: 0.1.12
Summary: 
License: GPL-2.0-only
Author: daniel
Author-email: dsal3389@dsal389.com
Requires-Python: >=3.10,<4.0
Classifier: License :: OSI Approved :: GNU General Public License v2 (GPLv2)
Classifier: Programming Language :: Python :: 3
Classifier: Programming Language :: Python :: 3.10
Requires-Dist: cleo (==1.0.0a4)
